spider_core/__init__.py
spider_core/cache_func.py
spider_core/config.py
spider_core/django.py
spider_core/encrypt.py
spider_core/es.py
spider_core/log.py
spider_core/mq_api.py
spider_core/mq_decode.py
spider_core/multi_process.py
spider_core/multi_thread_auto.py
spider_core/mysql.py
spider_core/parser.py
spider_core/queue.py
spider_core/queue0.py
spider_core/queue2.py
spider_core/redis.py
spider_core/robot.py
spider_core/sqlalchemy.py
spider_core/url_uuid.py
spider_core/utils.py
spider_core-0.1.4.dist-info/LICENSE
spider_core-0.1.4.dist-info/METADATA
spider_core-0.1.4.dist-info/WHEEL
spider_core-0.1.4.dist-info/top_level.txt
spider_core-0.1.4.dist-info/RECORD
