Metadata-Version: 2.1
Name: spider-core
Version: 0.1.4
Summary: 通用模块
Home-page: UNKNOWN
Author: lzl
License: UNKNOWN
Platform: UNKNOWN
Classifier: Programming Language :: Python :: 3
Classifier: License :: OSI Approved :: MIT License
Classifier: Operating System :: OS Independent
Requires-Python: >=3.6
License-File: LICENSE
Requires-Dist: pika
Requires-Dist: elasticsearch-dsl
Requires-Dist: pymysql
Requires-Dist: shortuuid
Requires-Dist: redis
Requires-Dist: threadpool
Requires-Dist: requests
Requires-Dist: pycrypto
